e85/Lab3/lab3_jf/thunderbird.sv
module thunderbird(
    input logic clk,
    input logic reset,
    input logic left, right,
    output logic la, lb, lc, ra, rb, rc
);

logic s2, s1, s0;
wire w0, w1, w2, w3, w4, w5, w6, w7, w8, w9;

and(w0, ~left, ~s0, ~s1, right);
nand(w1, s1, s0);
and(w2, w1, s2);
or(w3, w2, w0);
xor(w4, s0, s1);
xor(w5, left, right);
and(w6, w5, ~s0, ~s1);
and(w7, ~s0, s1);
or(w8, w7, w6);

flopr ff_s2(clk, reset, w3, s2);
flopr ff_s1(clk, reset, w4, s1);
flopr ff_s0(clk, reset, w8, s0);

or(w9, s1, s0);
and(la, w9, ~s2);
and(lb, s1, ~s2);
and(lc, s0, s1, ~s2);
and(ra, w9, s2);
and(rb, s1, s2);
and(rc, s0, s1, s2);
endmodule

module flopr(
    input  logic clk,
    input  logic reset,
    input  logic d,
    output logic q
);

    always_ff @(posedge clk) begin
        if (reset)
            q <= 0;
        else
            q <= d;
    end

endmodule

e85/Lab3/lab3_jf/thunderbird_tb.sv
module testbench();
  localparam int NUM_TEST_VECTORS = 14;

  logic clk, reset;
  logic left, right, la, lb, lc, ra, rb, rc;
  logic [5:0] expected;
  logic [31:0] vectornum, errors;
  logic [7:0] testvectors[10000:0];
  logic [7:0] vec;

  thunderbird dut(clk, reset, left, right, la, lb, lc, ra, rb, rc);

  initial clk = 0;
  always #5 clk = ~clk;

  initial begin
    integer i;

    $system("mkdir -p waves");
    $dumpfile("waves/thunderbird.vcd");
    $dumpvars(0, dut);

    $readmemb("thunderbird.tv", testvectors);
    vectornum = 0;
    errors = 0;
    reset = 1;

    repeat (3) @(posedge clk);
    reset = 0;

    for (i = 0; i < NUM_TEST_VECTORS; i = i + 1) begin
      @(posedge clk);
      vec = testvectors[i];

      #1;
      left = vec[7];
      right = vec[6];
      expected = {vec[5], vec[4], vec[3], vec[2], vec[1], vec[0]};

      @(negedge clk);
      if ({la, lb, lc, ra, rb, rc} !== expected) begin
        $display("Error: inputs = %b", {left, right});
        $display(" outputs = %b %b %b %b %b %b (%b expected)",
                 la, lb, lc, ra, rb, rc, expected);
        errors = errors + 1;
      end
      vectornum = vectornum + 1;
    end

    $display("%0d tests completed with %0d errors", vectornum, errors);
    $finish;
  end
endmodule

e85/Lab3/lab3_jf/waves/thunderbird.vcd
$version Generated by VerilatedVcd $end
$timescale 1ps $end
 $scope module TOP $end
  $scope module testbench $end
   $var wire 32 ? NUM_TEST_VECTORS [31:0] $end
   $var wire 1 : clk $end
   $var wire 1 # reset $end
   $var wire 1 $ left $end
   $var wire 1 % right $end
   $var wire 1 , la $end
   $var wire 1 - lb $end
   $var wire 1 . lc $end
   $var wire 1 / ra $end
   $var wire 1 0 rb $end
   $var wire 1 1 rc $end
   $var wire 6 & expected [5:0] $end
   $var wire 32 ' vectornum [31:0] $end
   $var wire 32 ( errors [31:0] $end
   $var wire 8 ) vec [7:0] $end
   $scope module dut $end
    $var wire 1 : clk $end
    $var wire 1 # reset $end
    $var wire 1 $ left $end
    $var wire 1 % right $end
    $var wire 1 , la $end
    $var wire 1 - lb $end
    $var wire 1 . lc $end
    $var wire 1 / ra $end
    $var wire 1 0 rb $end
    $var wire 1 1 rc $end
    $var wire 1 2 s2 $end
    $var wire 1 3 s1 $end
    $var wire 1 4 s0 $end
    $var wire 1 ; w0 $end
    $var wire 1 5 w1 $end
    $var wire 1 6 w2 $end
    $var wire 1 < w3 $end
    $var wire 1 7 w4 $end
    $var wire 1 * w5 $end
    $var wire 1 = w6 $end
    $var wire 1 8 w7 $end
    $var wire 1 > w8 $end
    $var wire 1 9 w9 $end
    $scope module ff_s0 $end
     $var wire 1 : clk $end
     $var wire 1 # reset $end
     $var wire 1 > d $end
     $var wire 1 4 q $end
    $upscope $end
    $scope module ff_s1 $end
     $var wire 1 : clk $end
     $var wire 1 # reset $end
     $var wire 1 7 d $end
     $var wire 1 3 q $end
    $upscope $end
    $scope module ff_s2 $end
     $var wire 1 : clk $end
     $var wire 1 # reset $end
     $var wire 1 < d $end
     $var wire 1 2 q $end
    $upscope $end
   $upscope $end
   $scope module unnamedblk1 $end
    $var wire 32 + i [31:0] $end
   $upscope $end
  $upscope $end
 $upscope $end
$enddefinitions $end


#0
1#
0$
0%
b000000 &
b00000000000000000000000000000000 '
b00000000000000000000000000000000 (
b00000000 )
0*
b00000000000000000000000000000000 +
0,
0-
0.
0/
00
01
02
03
04
15
06
07
08
09
0:
0;
0<
0=
0>
b00000000000000000000000000001110 ?
#5
1:
#10
0:
#15
1:
#20
0:
#25
0#
1:
#30
0:
#35
1:
#36
#40
b00000000000000000000000000000001 '
b00000000000000000000000000000001 +
0:
#45
b10000000 )
1:
#46
1$
1*
1=
1>
#50
b00000000000000000000000000000010 '
b00000000000000000000000000000010 +
0:
#55
b10100000 )
1,
14
17
19
1:
0=
0>
#56
b100000 &
#60
b00000000000000000000000000000011 '
b00000000000000000000000000000011 +
0:
#65
b10110000 )
1-
13
04
18
1:
1>
#66
b110000 &
#70
b00000000000000000000000000000100 '
b00000000000000000000000000000100 +
0:
#75
b10111000 )
1.
14
05
07
08
1:
0>
#76
b111000 &
#80
b00000000000000000000000000000101 '
b00000000000000000000000000000101 +
0:
#85
b10000000 )
0,
0-
0.
03
04
15
09
1:
1=
1>
#86
b000000 &
#90
b00000000000000000000000000000110 '
b00000000000000000000000000000110 +
0:
#95
b10100000 )
1,
14
17
19
1:
0=
0>
#96
b100000 &
#100
b00000000000000000000000000000111 '
b00000000000000000000000000000111 +
0:
#105
b00110000 )
1-
13
04
18
1:
1>
#106
0$
b110000 &
0*
#110
b00000000000000000000000000001000 '
b00000000000000000000000000001000 +
0:
#115
b01111000 )
1.
14
05
07
08
1:
0>
#116
1%
b111000 &
1*
#120
b00000000000000000000000000001001 '
b00000000000000000000000000001001 +
0:
#125
b01000000 )
0,
0-
0.
03
04
15
09
1:
1;
1<
1=
1>
#126
b000000 &
#130
b00000000000000000000000000001010 '
b00000000000000000000000000001010 +
0:
#135
b01000100 )
1/
12
14
16
17
19
1:
0;
0=
0>
#136
b000100 &
#140
b00000000000000000000000000001011 '
b00000000000000000000000000001011 +
0:
#145
b00000110 )
10
13
04
18
1:
1>
#146
0%
b000110 &
0*
#150
b00000000000000000000000000001100 '
b00000000000000000000000000001100 +
0:
#155
b00000111 )
11
14
05
06
07
08
1:
0<
0>
#156
b000111 &
#160
b00000000000000000000000000001101 '
b00000000000000000000000000001101 +
0:
#165
b00000000 )
0/
00
01
02
03
04
15
09
1:
#166
b000000 &
#170
b00000000000000000000000000001110 '
b00000000000000000000000000001110 +
0:
